ydiskarc/__init__.py
ydiskarc/__main__.py
ydiskarc/config.py
ydiskarc/core.py
ydiskarc/cmds/__init__.py
ydiskarc/cmds/processor.py
ydiskarc-1.1.0.dist-info/licenses/LICENSE
ydiskarc-1.1.0.dist-info/METADATA
ydiskarc-1.1.0.dist-info/WHEEL
ydiskarc-1.1.0.dist-info/entry_points.txt
ydiskarc-1.1.0.dist-info/top_level.txt
ydiskarc-1.1.0.dist-info/RECORD
