Metadata-Version: 2.4
Name: ydiskarc
Version: 1.1.0
Summary: Command-line tool to backup public resources from Yandex.Disk
Home-page: https://github.com/ruarxive/ydiskarc/
Download-URL: https://github.com/ruarxive/ydiskarc/
Author: Ivan Begtin
Author-email: Ivan Begtin <ivan@begtin.tech>
License: MIT
Project-URL: Homepage, https://github.com/ruarxive/ydiskarc/
Project-URL: Repository, https://github.com/ruarxive/ydiskarc/
Project-URL: Issues, https://github.com/ruarxive/ydiskarc/issues
Keywords: backup,archive,metadata,yandex,yandex-disk
Classifier: Development Status :: 5 - Production/Stable
Classifier: Programming Language :: Python
Classifier: Programming Language :: Python :: 3 :: Only
Classifier: Programming Language :: Python :: 3.6
Classifier: Programming Language :: Python :: 3.7
Classifier: Programming Language :: Python :: 3.8
Classifier: Programming Language :: Python :: 3.9
Classifier: Programming Language :: Python :: 3.10
Classifier: Programming Language :: Python :: 3.11
Classifier: Environment :: Console
Classifier: Intended Audience :: Developers
Classifier: Intended Audience :: System Administrators
Classifier: License :: OSI Approved :: MIT License
Classifier: Topic :: Software Development
Classifier: Topic :: System :: Networking
Classifier: Topic :: Terminals
Classifier: Topic :: Text Processing
Classifier: Topic :: Utilities
Requires-Python: >=3.6
License-File: LICENSE
Requires-Dist: typer>=0.9.0
Requires-Dist: PyYAML>=6.0.1
Requires-Dist: requests>=2.31.0
Requires-Dist: rich>=13.6.0
Provides-Extra: dev
Requires-Dist: pytest>=7.4.2; extra == "dev"
Requires-Dist: tox; extra == "dev"
Requires-Dist: docutils; extra == "dev"
Requires-Dist: wheel; extra == "dev"
Requires-Dist: twine; extra == "dev"
Requires-Dist: pygments>=2.7.4; extra == "dev"
Dynamic: author
Dynamic: download-url
Dynamic: home-page
Dynamic: license-file
